Metadata-Version: 1.0
Name: stable.world
Version: 0.0.0.post0.dev2
Summary: Build reliability tool
Home-page: UNKNOWN
Author: Sean Ross-Ross
Author-email: srossross@gmail.com
License: BSD
Platform: UNKNOWN
